LICENSE
MANIFEST.in
README.md
package.json
setup.py
dash_archer/DashArcher.py
dash_archer/DashArcherContainer.py
dash_archer/DashArcherElement.py
dash_archer/__init__.py
dash_archer/_imports_.py
dash_archer/dash_archer.min.js
dash_archer/dash_archer.min.js.map
dash_archer/metadata.json
dash_archer/package-info.json
dash_archer.egg-info/PKG-INFO
dash_archer.egg-info/SOURCES.txt
dash_archer.egg-info/dependency_links.txt
dash_archer.egg-info/top_level.txt