Metadata-Version: 1.1
Name: dash-archer
Version: 0.1.0
Summary: Dash component for react-archer
Home-page: UNKNOWN
Author: Tuomas Jaakola <tuomas.jaakola@iki.fi>
Author-email: UNKNOWN
License: MIT
Platform: UNKNOWN
Classifier: Framework :: Dash
